<?xml version="1.0" encoding="UTF-8"?>
<objects serializationModel="Studio.02.02.00">
	<object class="AudioFile" id="{d1e8ea0f-eeea-4fc7-9d8d-208eed6c2f98}">
		<property name="assetPath">
			<value>Cat/Steps/CatStep3.wav</value>
		</property>
		<property name="frequencyInKHz">
			<value>44.0999985</value>
		</property>
		<property name="channelCount">
			<value>2</value>
		</property>
		<property name="length">
			<value>6</value>
		</property>
		<relationship name="masterAssetFolder">
			<destination>{f3ccfe0a-4f9d-4604-8324-417a2d72bdb7}</destination>
		</relationship>
	</object>
</objects>
